setup.py
xgbmagic/__init__.py
xgbmagic/example.py
xgbmagic/xgbmagic.py
xgbmagic.egg-info/PKG-INFO
xgbmagic.egg-info/SOURCES.txt
xgbmagic.egg-info/dependency_links.txt
xgbmagic.egg-info/not-zip-safe
xgbmagic.egg-info/requires.txt
xgbmagic.egg-info/top_level.txt