Metadata-Version: 1.0
Name: xgbmagic
Version: 0.0.3.2
Summary: Data preprocessing and analysis using XGBoost
Home-page: http://github.com/mirri66/xgbmagic
Author: Grace Tang
Author-email: tsmgrace@gmail.com
License: MIT
Platform: UNKNOWN
